gh_folder_download/__init__.py
gh_folder_download/__main__.py
gh_folder_download/cache.py
gh_folder_download/config.py
gh_folder_download/filters.py
gh_folder_download/integrity.py
gh_folder_download/logger.py
gh_folder_download/main.py
gh_folder_download/parallel_downloader.py
gh_folder_download/progress.py
gh_folder_download/rate_limiter.py
gh_folder_download/retry.py
gh_folder_download/validation.py
gh_folder_download-1.0.0.dist-info/METADATA
gh_folder_download-1.0.0.dist-info/WHEEL
gh_folder_download-1.0.0.dist-info/entry_points.txt
gh_folder_download-1.0.0.dist-info/RECORD
