Metadata-Version: 2.4
Name: gh-folder-download
Version: 1.0.0
Summary: A command line application (CLI) to download only a specific folder without downloading the full repository implemented with Python using Typer and GitHub API.
Project-URL: homepage, https://github.com/leynier/gh-folder-download
Project-URL: repository, https://github.com/leynier/gh-folder-download
Project-URL: documentation, https://github.com/leynier/gh-folder-download
Project-URL: issues, https://github.com/leynier/gh-folder-download/issues
Author-email: Leynier Gutiérrez González <leynier41@gmail.com>
Maintainer-email: Leynier Gutiérrez González <leynier41@gmail.com>
License: MIT
Keywords: cli,download,folder,github
Classifier: License :: OSI Approved :: MIT License
Classifier: Operating System :: OS Independent
Classifier: Programming Language :: Python :: 3
Requires-Python: >=3.12
Requires-Dist: aiohttp>=3.12.6
Requires-Dist: pydantic>=2.11.5
Requires-Dist: pygithub>=2.6.1
Requires-Dist: pyyaml>=6.0.2
Requires-Dist: requests>=2.32.3
Requires-Dist: rich>=14.0.0
Requires-Dist: typer>=0.16.0
